ppstructure/__init__.py
ppstructure/predict_system.py
ppstructure/utility.py
ppstructure/layout/__init__.py
ppstructure/layout/predict_layout.py
ppstructure/recovery/__init__.py
ppstructure/recovery/recovery_to_doc.py
ppstructure/recovery/table_process.py
ppstructure/table/__init__.py
ppstructure/table/convert_label2html.py
ppstructure/table/eval_table.py
ppstructure/table/matcher.py
ppstructure/table/predict_structure.py
ppstructure/table/predict_table.py
ppstructure/table/table_master_match.py
ppstructure/table/table_metric/__init__.py
ppstructure/table/table_metric/parallel.py
ppstructure/table/table_metric/table_metric.py
ppstructure/table/tablepyxl/__init__.py
ppstructure/table/tablepyxl/style.py
ppstructure/table/tablepyxl/tablepyxl.py
tools/__init__.py
anlab_paddleocr-0.0.1.dist-info/LICENSE
anlab_paddleocr-0.0.1.dist-info/METADATA
anlab_paddleocr-0.0.1.dist-info/WHEEL
anlab_paddleocr-0.0.1.dist-info/top_level.txt
anlab_paddleocr-0.0.1.dist-info/RECORD
