Metadata-Version: 2.1
Name: anlab-paddleocr
Version: 0.0.1
Summary: UNKNOWN
Home-page: UNKNOWN
Author: Anlab
Author-email: cuong.dvt@anlab.asia
License: MIT
Platform: UNKNOWN
Classifier: Programming Language :: Python :: 3
Classifier: License :: OSI Approved :: MIT License
Classifier: Operating System :: OS Independent
License-File: LICENSE
